free_proxy_server/__init__.py
free_proxy_server/async_client.py
free_proxy_server/client.py
free_proxy_server/exceptions.py
free_proxy_server/models.py
free_proxy_server/utils.py
free_proxy_server-1.0.0.dist-info/licenses/LICENSE
tests/__init__.py
tests/test_basic.py
free_proxy_server-1.0.0.dist-info/METADATA
free_proxy_server-1.0.0.dist-info/WHEEL
free_proxy_server-1.0.0.dist-info/top_level.txt
free_proxy_server-1.0.0.dist-info/RECORD
